CREDITS.txt
LICENSE.txt
MANIFEST.in
README.txt
setup.py
django_permissions.egg-info/PKG-INFO
django_permissions.egg-info/SOURCES.txt
django_permissions.egg-info/dependency_links.txt
django_permissions.egg-info/not-zip-safe
django_permissions.egg-info/pbr.json
django_permissions.egg-info/requires.txt
django_permissions.egg-info/top_level.txt
permissions/__init__.py
permissions/admin.py
permissions/backend.py
permissions/exceptions.py
permissions/models.py
permissions/tests.py
permissions/utils.py
permissions/fixtures/initial.xml
permissions/locale/de/LC_MESSAGES/django.mo
permissions/locale/de/LC_MESSAGES/django.po
permissions/migrations/0001_initial.py
permissions/migrations/__init__.py
permissions/templatetags/__init__.py
permissions/templatetags/permissions_tags.py